[
  {"chapter": 1, "character_id": "liu_bei", "status_label": "起势", "status_detail": "目睹黄巾乱局，开始招募义勇。", "event_ids": ["ev_yellow_turban", "ev_peach_oath"]},
  {"chapter": 1, "character_id": "guan_yu", "status_label": "结义", "status_detail": "与刘备张飞结义，确立共同使命。", "event_ids": ["ev_peach_oath"]},
  {"chapter": 1, "character_id": "zhang_fei", "status_label": "聚义", "status_detail": "出资募兵，成为团队后勤与武力支点。", "event_ids": ["ev_peach_oath"]},
  {"chapter": 1, "character_id": "cao_cao", "status_label": "初露", "status_detail": "以干练形象进入乱世叙事。", "event_ids": ["ev_yellow_turban"]},
  {"chapter": 3, "character_id": "dong_zhuo", "status_label": "入京", "status_detail": "借朝廷混乱控制中央军政。", "event_ids": ["ev_dong_chaos"]},
  {"chapter": 3, "character_id": "lu_bu", "status_label": "依附", "status_detail": "追随董卓，在武力结构中上位。", "event_ids": ["ev_dong_chaos"]},
  {"chapter": 4, "character_id": "han_xiandi", "status_label": "受制", "status_detail": "被董卓拥立后缺乏实权。", "event_ids": ["ev_dong_chaos"]},
  {"chapter": 5, "character_id": "yuan_shao", "status_label": "盟主", "status_detail": "组织诸侯联军，名望达到高点。", "event_ids": ["ev_hulao"]},
  {"chapter": 5, "character_id": "sun_jian", "status_label": "先登", "status_detail": "率军讨董，战绩突出。", "event_ids": ["ev_hulao"]},
  {"chapter": 5, "character_id": "liu_bei", "status_label": "会战", "status_detail": "与关张参与虎牢关会战。", "event_ids": ["ev_hulao"]},
  {"chapter": 5, "character_id": "guan_yu", "status_label": "猛将", "status_detail": "在会战中展示超强战力。", "event_ids": ["ev_hulao"]},
  {"chapter": 5, "character_id": "zhang_fei", "status_label": "突击", "status_detail": "与关羽协同冲阵。", "event_ids": ["ev_hulao"]},
  {"chapter": 5, "character_id": "lu_bu", "status_label": "守关", "status_detail": "作为董卓阵营核心战力迎战。", "event_ids": ["ev_hulao"]},
  {"chapter": 9, "character_id": "dong_zhuo", "status_label": "覆灭", "status_detail": "在宫廷政变中被诛。", "event_ids": []},
  {"chapter": 14, "character_id": "cao_cao", "status_label": "中枢", "status_detail": "迎献帝至许都，掌握政治正统。", "event_ids": ["ev_xudu"]},
  {"chapter": 14, "character_id": "han_xiandi", "status_label": "迁都", "status_detail": "随曹操迁至许都，皇权继续名义化。", "event_ids": ["ev_xudu"]},
  {"chapter": 19, "character_id": "lu_bu", "status_label": "终局", "status_detail": "下邳兵败后人生线终止。", "event_ids": []},
  {"chapter": 21, "character_id": "liu_bei", "status_label": "游走", "status_detail": "在强敌间寻求生存与发展空间。", "event_ids": []},
  {"chapter": 25, "character_id": "guan_yu", "status_label": "守义", "status_detail": "短暂寄身曹营仍不改本心。", "event_ids": []},
  {"chapter": 27, "character_id": "guan_yu", "status_label": "归队", "status_detail": "过五关斩六将后回归刘备。", "event_ids": []},
  {"chapter": 29, "character_id": "sun_ce", "status_label": "江东主线", "status_detail": "江东政权持续扩张，孙策线接近终章。", "event_ids": []},
  {"chapter": 30, "character_id": "cao_cao", "status_label": "决战", "status_detail": "官渡决战主动求变，转守为攻。", "event_ids": ["ev_guandu"]},
  {"chapter": 30, "character_id": "yuan_shao", "status_label": "失机", "status_detail": "优势兵力未转化为胜势。", "event_ids": ["ev_guandu"]},
  {"chapter": 31, "character_id": "cao_cao", "status_label": "北方主导", "status_detail": "官渡后继续扩大统治基础。", "event_ids": ["ev_guandu"]},
  {"chapter": 31, "character_id": "yuan_shao", "status_label": "衰落", "status_detail": "势力分裂，难以恢复。", "event_ids": ["ev_guandu"]},
  {"chapter": 34, "character_id": "liu_bei", "status_label": "驻新野", "status_detail": "在荆州边缘地带整军蓄势。", "event_ids": ["ev_jingzhou_refuge"]},
  {"chapter": 34, "character_id": "guan_yu", "status_label": "守备", "status_detail": "随刘备驻屯荆州北缘。", "event_ids": ["ev_jingzhou_refuge"]},
  {"chapter": 34, "character_id": "zhang_fei", "status_label": "整训", "status_detail": "负责军队训练与防务。", "event_ids": ["ev_jingzhou_refuge"]},
  {"chapter": 35, "character_id": "cao_cao", "status_label": "压境", "status_detail": "持续对刘备形成战略压力。", "event_ids": ["ev_jingzhou_refuge"]},
  {"chapter": 37, "character_id": "liu_bei", "status_label": "求贤", "status_detail": "多次拜访卧龙草庐。", "event_ids": ["ev_three_visits"]},
  {"chapter": 37, "character_id": "zhuge_liang", "status_label": "待时", "status_detail": "审视时局与来者诚意。", "event_ids": ["ev_three_visits"]},
  {"chapter": 37, "character_id": "guan_yu", "status_label": "随行", "status_detail": "在求贤行动中护卫刘备。", "event_ids": ["ev_three_visits"]},
  {"chapter": 37, "character_id": "zhang_fei", "status_label": "急躁", "status_detail": "对反复拜访心有不耐。", "event_ids": ["ev_three_visits"]},
  {"chapter": 38, "character_id": "liu_bei", "status_label": "定策", "status_detail": "接受隆中对，确定三分战略。", "event_ids": ["ev_three_visits"]},
  {"chapter": 38, "character_id": "zhuge_liang", "status_label": "出山", "status_detail": "正式加入刘备集团。", "event_ids": ["ev_three_visits"]},
  {"chapter": 38, "character_id": "cao_cao", "status_label": "北方强权", "status_detail": "成为未来三分格局中的最大外部压力。", "event_ids": []},
  {"chapter": 38, "character_id": "han_xiandi", "status_label": "名义皇权", "status_detail": "仍居政治名义中心。", "event_ids": []}
]
